mimeparse.py
python_mimeparse-1.5.5.dist-info/DESCRIPTION.rst
python_mimeparse-1.5.5.dist-info/METADATA
python_mimeparse-1.5.5.dist-info/RECORD
python_mimeparse-1.5.5.dist-info/WHEEL
python_mimeparse-1.5.5.dist-info/metadata.json
python_mimeparse-1.5.5.dist-info/top_level.txt
