Metadata-Version: 2.0
Name: python-mimeparse
Version: 1.5.5
Summary: A module provides basic functions for parsing mime-type names and matching them against a list of media-ranges.
Home-page: https://github.com/dbtsai/python-mimeparse
Author: DB Tsai
Author-email: dbtsai@dbtsai.com
License: UNKNOWN
Download-URL: https://github.com/dbtsai/python-mimeparse/tarball/1.5.5
Keywords: mime-type
Platform: UNKNOWN
Classifier: Programming Language :: Python
Classifier: Programming Language :: Python :: 3
Classifier: License :: OSI Approved :: MIT License
Classifier: Operating System :: OS Independent
Classifier: Development Status :: 5 - Production/Stable
Classifier: Intended Audience :: Developers
Classifier: Topic :: Internet :: WWW/HTTP
Classifier: Topic :: Software Development :: Libraries :: Python Modules
